README.txt
setup.py
Ctrax/Ctrax.py
Ctrax/FlyMovieFormat.py
Ctrax/FlyMovieFormat_bak.py
Ctrax/__init__.py
Ctrax/about.py
Ctrax/algorithm.py
Ctrax/annfiles.py
Ctrax/batch.py
Ctrax/bg.py
Ctrax/chooseorientations.py
Ctrax/colormapk.py
Ctrax/draw.py
Ctrax/ellipsesk.py
Ctrax/estconncomps.py
Ctrax/fixbg.py
Ctrax/highboostfilter.py
Ctrax/hindsight.py
Ctrax/histgmm.py
Ctrax/houghcircles.py
Ctrax/imagesk.py
Ctrax/kcluster.py
Ctrax/kcluster2d.py
Ctrax/matchidentities.py
Ctrax/medmad.py
Ctrax/movies.py
Ctrax/newFlyMovieFormat.py
Ctrax/newavi.py
Ctrax/newestconncomps.py
Ctrax/newmovies.py
Ctrax/params.py
Ctrax/roi.py
Ctrax/setarena.py
Ctrax/settings.py
Ctrax/simple_overlay_backup.py
Ctrax/static_background_fmf.py
Ctrax/tracking_settings.py
Ctrax/version.py
Ctrax.egg-info/PKG-INFO
Ctrax.egg-info/SOURCES.txt
Ctrax.egg-info/dependency_links.txt
Ctrax.egg-info/eager_resources.txt
Ctrax.egg-info/entry_points.txt
Ctrax.egg-info/stdeb.cfg
Ctrax.egg-info/top_level.txt
houghcircles/houghcircles_C.c
hungarian/asp.cpp
hungarian/hungarian.cpp