Metadata-Version: 1.0
Name: Ctrax
Version: 0.1.5.3
Summary: Multiple fly tracker
Home-page: http://www.dickinson.caltech.edu/Ctrax
Author: Caltech ethomics project
Author-email: branson@caltech.edu
License: UNKNOWN
Platform: UNKNOWN
